evalscope_perf/__init__.py
evalscope_perf/main.py
evalscope_perf-0.1.6.dist-info/LICENSE
evalscope_perf-0.1.6.dist-info/METADATA
evalscope_perf-0.1.6.dist-info/WHEEL
evalscope_perf-0.1.6.dist-info/entry_points.txt
evalscope_perf-0.1.6.dist-info/top_level.txt
evalscope_perf-0.1.6.dist-info/RECORD
