Metadata-Version: 2.1
Name: evalscope-perf
Version: 0.1.6
Summary: 大模型性能压测可视化
Home-page: http://www.wangjunjian.com
Author: Junjian Wang
Author-email: vwarship@163.com
Classifier: Programming Language :: Python :: 3
Classifier: License :: OSI Approved :: MIT License
Classifier: Operating System :: OS Independent
Requires-Python: >=3.6
License-File: LICENSE
Requires-Dist: typer
Requires-Dist: pandas
Requires-Dist: matplotlib
